{
  "project_info": {
    "project_number": "253121042757",
    "project_id": "proyecto-new-37f18",
    "storage_bucket": "proyecto-new-37f18.firebasestorage.app"
  },
  "client": [
    {
      "client_info": {
        "mobilesdk_app_id": "1:253121042757:android:45b5961c0196fb698b862c",
        "android_client_info": {
          "package_name": "com.example.aplicacionnuevaprueba1"
        }
      },
      "oauth_client": [],
      "api_key": [
        {
          "current_key": "AIzaSyC1BCgvd2n0tfhhqoAKyEvglnUpxlUoDKo"
        }
      ],
      "services": {
        "appinvite_service": {
          "other_platform_oauth_client": []
        }
      }
    }
  ],
  "configuration_version": "1"
}